logfiles/.DS_Store
logfiles/__init__.py
logfiles/admin.py
logfiles/apps.py
logfiles/models.py
logfiles/settings.py
logfiles/tests.py
logfiles/static/.DS_Store
logfiles/static/admin/.DS_Store
logfiles/static/admin/css/logfile.css
django_logfiles-1.0.3.dist-info/METADATA
django_logfiles-1.0.3.dist-info/WHEEL
django_logfiles-1.0.3.dist-info/licenses/LICENSE
django_logfiles-1.0.3.dist-info/RECORD
