Metadata-Version: 2.1
Name: django-logfiles
Version: 1.0.3
Summary: Plugin to show logfiles in the admin pane of a django project
Project-URL: Homepage, https://github.com/rwestein/django-logfiles
Project-URL: Issues, https://github.com/rwestein/django-logfiles/issues
Author-email: Ronnie van 't Westeinde <info@westeron.net>
License-File: LICENSE
Classifier: License :: OSI Approved :: MIT License
Classifier: Operating System :: OS Independent
Classifier: Programming Language :: Python :: 3
Requires-Python: >=3.6
